{
  "doc_type": "ppt",
  "file_name": "50S新器件部件验证进度-20250224.pptx",
  "tables": [
    {
      "sheet": "电池包开发进度",
      "data": "类型,型号,优选料号,推荐料号\r\n5pin方形包5200,R2412普通版,\"明美比克03020200000186（已量产）\n欣动亿纬03020200000226（海外生产优势）\",\"明美远东03020200000178（认证全，已量产）\n飞毛腿亿纬03020200000249\"\r\n5pin方形包5200,R2412美版,明美比克03020200000198（已量产）,欣动亿纬03020200000212（海外生产优势）\r\n5pin方形包6400,R2416普通版,\"欣动亿纬03020200000144（已量产，海外生产优势）\n明美比克03020200000185（已量产）\",\"明美远东03020200000238\n飞毛腿亿纬03020200000248（新电芯）\"\r\n5pin方形包6400,R2416美版,欣动亿纬03020200000151（已量产，海外生产优势）,明美比克03020200000215\r\n5pin菱形包5200,R9445普通版,\"欣动亿纬03020200000243（海外生产优势）\n明美比克03020200000227\",飞毛腿远东03020200000234（海外生产优势）\r\n5pin菱形包5200,R9445美版,欣动亿纬03020200000267,飞毛腿远东，料号暂无\r\n5pin菱形包6400,R2401普通版,\"欣动亿纬03020200000145（已量产，海外生产优势）\n欣动比克03020200000266（新电芯）\",\"明美远东03020200000213\n飞毛腿亿纬03020200000233（新电芯）\"\r\n5pin菱形包6400,R2401美版,欣动亿纬03020200000194（已量产，海外生产优势）,明美远东03020200000237\r\n",
      "rows": [
        {
          "类型": "5pin方形包5200",
          "型号": "R2412普通版",
          "优选料号": "明美比克03020200000186（已量产）\n欣动亿纬03020200000226（海外生产优势）",
          "推荐料号": "明美远东03020200000178（认证全，已量产）\n飞毛腿亿纬03020200000249"
        },
        {
          "类型": "5pin方形包5200",
          "型号": "R2412美版",
          "优选料号": "明美比克03020200000198（已量产）",
          "推荐料号": "欣动亿纬03020200000212（海外生产优势）"
        },
        {
          "类型": "5pin方形包6400",
          "型号": "R2416普通版",
          "优选料号": "欣动亿纬03020200000144（已量产，海外生产优势）\n明美比克03020200000185（已量产）",
          "推荐料号": "明美远东03020200000238\n飞毛腿亿纬03020200000248（新电芯）"
        },
        {
          "类型": "5pin方形包6400",
          "型号": "R2416美版",
          "优选料号": "欣动亿纬03020200000151（已量产，海外生产优势）",
          "推荐料号": "明美比克03020200000215"
        },
        {
          "类型": "5pin菱形包5200",
          "型号": "R9445普通版",
          "优选料号": "欣动亿纬03020200000243（海外生产优势）\n明美比克03020200000227",
          "推荐料号": "飞毛腿远东03020200000234（海外生产优势）"
        },
        {
          "类型": "5pin菱形包5200",
          "型号": "R9445美版",
          "优选料号": "欣动亿纬03020200000267",
          "推荐料号": "飞毛腿远东，料号暂无"
        },
        {
          "类型": "5pin菱形包6400",
          "型号": "R2401普通版",
          "优选料号": "欣动亿纬03020200000145（已量产，海外生产优势）\n欣动比克03020200000266（新电芯）",
          "推荐料号": "明美远东03020200000213\n飞毛腿亿纬03020200000233（新电芯）"
        },
        {
          "类型": "5pin菱形包6400",
          "型号": "R2401美版",
          "优选料号": "欣动亿纬03020200000194（已量产，海外生产优势）",
          "推荐料号": "明美远东03020200000237"
        }
      ],
      "text": "电池包开发进度\n主机电池包---唐蕾\n*料号暂无物料，后期随项目需求申请料号安排测试验证，同项目建议搭配优选1+推荐1使用\n项目使用推荐料号\nPACK、电芯量产进度汇总；"
    }
  ]
}