{
  "doc_id": "0",
  "doc_type": "excel",
  "file_name": "电子元器件规格归一V02-20240628.xlsx",
  "tables": [
    {
      "sheet": "电阻",
      "data": "一,采样电阻,Column_3,Column_4,Column_5,Column_6,Column_7,Column_8,Column_9,Column_10,Column_11,Column_12,Column_13,Column_14,Column_15,Column_16,Column_17,Column_18\r\n序号,机型,使用位置,编码,描述,制造商名称,制造商料号,优选等级,封装,类型,标称阻值,精度(%),额定功率,最大工作电压(V),备注,,,\r\n1,主机,风机电流、充电IC输入/出电流,04160100000105,Resistor_Metal Foil_0.01R_1 %_1206_PE1206FKE470R01Z_Yageo,国巨,PE1206FKE470R01Z,2-推荐,1206,Metal Foil,0.01R,0.01,1W,,,,,\r\n1,主机,风机电流、充电IC输入/出电流,04160100000201,Resistor_Metal Film_0.01R_1 %_1206_RLM12FTCMR010_TA-I,大毅,RLM12FTCMR010,2-推荐,1206,Metal Film,0.01R,0.01,1W,,,,,\r\n1,主机,风机电流、充电IC输入/出电流,04160100001143,Resistor_Metal Foil_0.01R_1 %_1206_MS061WF100MT5E_Uni-Royal,厚声,MS061WF100MT5E,1-优选,1206,Metal Foil,0.01R,0.01,1W,,,,,\r\n2,主机,整机充放电流检测,04160100001019,Resistor_Metal Plate / Grid_0.02R_1 %_1206_PA1206FRF470R02L_Yageo,国巨,PA1206FRF470R02L,2-推荐,1206,Metal Plate / Grid,0.02R,0.01,1W,,,,,\r\n2,主机,整机充放电流检测,04160100001180,Resistor_Metal Foil_0.02R_1 %_1206_RLM12FTCMR020_TA-I,大毅,RLM12FTCMR020,2-推荐,1206,Metal Foil,0.02R,0.01,1W,,,,,\r\n2,主机,整机充放电流检测,04160100001178,Resistor_Metal Foil_0.02R_1 %_1206_MS061WF200MT5E_Uni-Royal,厚声,MS061WF200MT5E,1-优选,1206,Metal Foil,0.02R,0.01,1W,,,,,\r\n3,主机,驱动轮电流检测,04160100000106,Resistor_Thick Film_0.033R_1 %_1210_RL1210FR-070R033L_Yageo,国巨,RL1210FR-070R033L,4-新品禁用,1210,Thick Film,0.033R,0.01,1/2W,200 V,归一到2组0.02R,,,\r\n3,主机,驱动轮电流检测,04160100001132,Resistor_Thick Film_0.033R_1 %_1210_1210W2F330MT5E_Uni-Royal,厚声,1210W2F330MT5E,4-新品禁用,1210,Thick Film,0.033R,0.01,1/2W,200 V,归一到2组0.02R,,,\r\n4,基站,清水泵、蠕动泵、自动下水泵,04160100001228,Resistor_Thick Film_0.05R_1 %_1210_RL1210FR-070R05L_Yageo,国巨,RL1210FR-070R05L,4-新品禁用,1210,Thick Film,0.05R,0.01,1/2W,,归一到2组0.02R,,,\r\n4,基站,清水泵、蠕动泵、自动下水泵,04160100000799,Resistor_Thick Film_0.05R_1 %_1210_1210W2F500MT5E_Uni-Royal,厚声,1210W2F500MT5E,4-新品禁用,1210,Thick Film,0.05R,0.01,1/2W,200 V,归一到2组0.02R,,,\r\n5,基站,主机充电电流,04160100001048,Resistor_Metal Plate / Grid_0.05R_1 %_1206_PA1206FRF470R05L_Yageo,国巨,PA1206FRF470R05L,4-新品禁用,1206,Metal Film,0.05R,0.01,1W,,归一到2组0.02R,,,\r\n5,基站,主机充电电流,04160100001049,Resistor_Metal Foil_0.05R_1 %_1206_RLM12FTCMR050_TA-I,大毅,RLM12FTCMR050,4-新品禁用,1206,Metal Film,0.05R,0.01,1W,,归一到2组0.02R,,,\r\n6,主机,电池电流检测；风机电流检测,04160100000008,Resistor_Metal Foil_0.05R_1 %_2010_PE2010FKM7W0R05Z_Yageo,国巨,PE2010FKM7W0R05Z,2-推荐,2010,Metal Foil,0.05R,0.01,1W,,归一到2组0.02R,,,\r\n6,主机,电池电流检测；风机电流检测,04160100001229,Resistor_Metal Foil_0.05R_1 %_2010_MS101WF500MT4E_Uni-Royal,厚声,MS101WF500MT4E,5-淘汰,2010,Metal Foil,0.05R,0.01,1W,,归一到2组0.02R,,,\r\n6,主机,电池电流检测；风机电流检测,04160100001231,Resistor_Metal Foil_0.05R_1 %_2010_MS101AF500MT4E_Uni-Royal,厚声,MS101AF500MT4E,3-普通,2010,Metal Foil,0.05R,0.01,1.5W,,归一到2组0.02R,,,\r\n6,主机,电池电流检测；风机电流检测,04160100000213,Resistor_Metal Foil_0.05R_1 %_2010_STE2010M1W5R050F_Walter,华德,STE2010M1W5R050F,3-普通,2010,Metal Plate / Grid,0.05R,0.01,1.5W,,归一到2组0.02R,,,\r\n7,基站,电解水,04160100000719,Resistor_Thick_0.2R_1206W4F200LT5E_UNI-ROYAL,厚声,1206W4F200LT5E,1-优选,1206,Thick Film,0.2R,0.01,1/4W,200 V,电解水恒流500mA驱动，电解水用0.33R检流电阻在700~800TDS水质情况下会触发欠压保护，需要更换为0.2R检流电阻  ,,,\r\n7,基站,电解水,04160100001230,Resistor_Thick Film_0.2R_1 %_1206_RL1206FR-070R2L_Yageo,国巨,RL1206FR-070R2L,2-推荐,1206,Thick Film,0.2R,0.01,1/4W,200 V,电解水恒流500mA驱动，电解水用0.33R检流电阻在700~800TDS水质情况下会触发欠压保护，需要更换为0.2R检流电阻  ,,,\r\n8,主机、基站,自动上水电磁阀采样、边刷电流检测、进水泵/出水泵电流检测、电磁阀采样,04160100001153,Resistor_Metal Film_0.33R_1 %_1206_TL06W2F330LT5E_Uni-Royal,厚声,TL06W2F330LT5E,1-优选,1206,Metal Film,0.33R,0.01,1/2W,,,,,\r\n8,主机、基站,自动上水电磁阀采样、边刷电流检测、进水泵/出水泵电流检测、电磁阀采样,04160100000141,Resistor_Thick Film_0.33R_1 %_1206_RL12FTNR330_TA-I,大毅,RL12FTNR330,2-推荐,1206,alloy film chip,0.33R,0.01,1/2W,,,,,\r\n8,主机、基站,自动上水电磁阀采样、边刷电流检测、进水泵/出水泵电流检测、电磁阀采样,04160100001244,Resistor_Metal Film_0.33R_1 %_1206_PE1206FRF7W0R33L_Yageo,国巨,PE1206FRF7W0R33L,2-推荐,1206,Metal Film,0.33R,0.01,1/2W,,,,,\r\n8,主机、基站,自动上水电磁阀采样、边刷电流检测、进水泵/出水泵电流检测、电磁阀采样,04160100001292,Resistor_Metal Foil_0.33R_1 %_1206_STE1206M1W0R330F_Walter,华德,STE1206M1W0R330F,3-普通,1206,Metal Foil,0.33R,0.01,1W,,边刷位置,,,\r\n8,主机、基站,自动上水电磁阀采样、边刷电流检测、进水泵/出水泵电流检测、电磁阀采样,04160100001293,Resistor_Thick Film_0.33R_1 %_1206_RL1206FR-7W0R33L_Yageo,国巨,RL1206FR-7W0R33L,3-普通,1206,Thick Film,0.33R,0.01,1/2W,,非边刷位置可以使用厚膜电阻,,,\r\n9,基站,基站两位三通阀、UV灯；主机补光灯AI-LED  AW9967DNR,04160100000083,Resistor_Thick Film_1R_1 %_1206_RC1206FR-071RL_Yageo,国巨,RC1206FR-071RL,1-优选,1206,Thick Film,1R,0.01,1/4W,200 V,,,,\r\n9,基站,基站两位三通阀、UV灯；主机补光灯AI-LED  AW9967DNR,04160100001164,Resistor_Thick Film_1R_1 %_1206_1206W4F100KT5E_Uni-Royal,厚声,1206W4F100KT5E,2-推荐,1206,Thick Film,1R,0.01,1/4W,200 V,,,,\r\n10,基站,UV灯驱动采样电阻,04160100001236,Resistor_Thick Film_1.6R_1 %_1206_HP06W2F160KT5E_Uni-Royal,厚声,HP06W2F160KT5E,4-新品禁用,1206,Thick Film,1.6R,0.01,1/2W,200 V,归一到11组的2R,,,\r\n10,基站,UV灯驱动采样电阻,04160100001237,Resistor_Thick Film_1.6R_1 %_1206_RC1206FR-071R6L_Yageo,国巨,RC1206FR-071R6L,4-新品禁用,1206,Thick Film,1.6R,0.01,1/2W,200 V,归一到11组的2R,,,\r\n10,基站,UV灯驱动采样电阻,04160100001238,Resistor_Thick Film_1.6R_1 %_1206_RMH12FT1R60_TA-I,大毅,RMH12FT1R60,4-新品禁用,1206,Thick Film,1.6R,0.01,1/2W,200 V,归一到11组的2R,,,\r\n11,主机,补光灯限流电阻,04160100000798,Resistor_Thick Film_2R_1 %_1206_1206W4F200KT5E_Uni-Royal,厚声,1206W4F200KT5E,1-优选,1206,Thick Film,2R,0.01,1/4W,200 V,,,,\r\n11,主机,补光灯限流电阻,04160100001239,Resistor_Thick Film_2R_1 %_1206_RC1206FR-072RL_Yageo,国巨,RC1206FR-072RL,2-推荐,1206,Thick Film,2R,0.01,1/4W,200 V,,,,\r\n二,普通电阻,,,,,,,,,,,,,,,,\r\n,精度,金属、厚膜电阻：优选1%；薄膜电阻：优选0.1%,,,,,,,,,,,,,,,\r\n,尺寸,金属电阻尺寸：优选1206，其次：2010,,,,,,,,,,,,,,,\r\n,抗硫化电阻,禁用,,,,,,,,,,,,,,,\r\n,阻值：,E192 系列包含了 95 个基本阻值，分别为 1.0、1.1、1.2、1.3、1.5、1.6、1.8、2.0、2.2、2.4、2.7、3.0、3.3、3.6、3.9、4.3、4.7、5.1、5.6、6.2、6.8、7.5、8.2、9.1、10、11、12、13、15、16、18、20、22、24、27、30、33、36、39、43、47、51、56、62、68、75、82、91、100、110、120、130、150、160、180、200、220、240、270、300、330、360、390、430、470、510、560、620、680、750、820、910、1.0K、1.1K、1.2K、1.3K、1.5K、1.6K、1.8K、2.0K、2.2K、2.4K、2.7K、3.0K、3.3K、3.6K、3.9K、4.3K、4.7K、5.1K、5.6K、6.2K、6.8K、7.5K、8.2K、9.1K、10K、11K、12K、13K、15K、16K、18K、20K、22K、24K、27K、30K、33K、36K、39K、43K、47K、51K、56K、62K、68K、75K、82K、91K、100K、110K、120K、130K、150K、160K、180K、200K、220K、240K、270K、300K、330K、360K、390K、430K、470K、510K、560K、620K、680K、750K、820K、910K、1M、1.1M、1.2M、1.3M、1.5M、1.6M、1.8M,E192 系列包含了 95 个基本阻值，分别为 1.0、1.1、1.2、1.3、1.5、1.6、1.8、2.0、2.2、2.4、2.7、3.0、3.3、3.6、3.9、4.3、4.7、5.1、5.6、6.2、6.8、7.5、8.2、9.1、10、11、12、13、15、16、18、20、22、24、27、30、33、36、39、43、47、51、56、62、68、75、82、91、100、110、120、130、150、160、180、200、220、240、270、300、330、360、390、430、470、510、560、620、680、750、820、910、1.0K、1.1K、1.2K、1.3K、1.5K、1.6K、1.8K、2.0K、2.2K、2.4K、2.7K、3.0K、3.3K、3.6K、3.9K、4.3K、4.7K、5.1K、5.6K、6.2K、6.8K、7.5K、8.2K、9.1K、10K、11K、12K、13K、15K、16K、18K、20K、22K、24K、27K、30K、33K、36K、39K、43K、47K、51K、56K、62K、68K、75K、82K、91K、100K、110K、120K、130K、150K、160K、180K、200K、220K、240K、270K、300K、330K、360K、390K、430K、470K、510K、560K、620K、680K、750K、820K、910K、1M、1.1M、1.2M、1.3M、1.5M、1.6M、1.8M,E192 系列包含了 95 个基本阻值，分别为 1.0、1.1、1.2、1.3、1.5、1.6、1.8、2.0、2.2、2.4、2.7、3.0、3.3、3.6、3.9、4.3、4.7、5.1、5.6、6.2、6.8、7.5、8.2、9.1、10、11、12、13、15、16、18、20、22、24、27、30、33、36、39、43、47、51、56、62、68、75、82、91、100、110、120、130、150、160、180、200、220、240、270、300、330、360、390、430、470、510、560、620、680、750、820、910、1.0K、1.1K、1.2K、1.3K、1.5K、1.6K、1.8K、2.0K、2.2K、2.4K、2.7K、3.0K、3.3K、3.6K、3.9K、4.3K、4.7K、5.1K、5.6K、6.2K、6.8K、7.5K、8.2K、9.1K、10K、11K、12K、13K、15K、16K、18K、20K、22K、24K、27K、30K、33K、36K、39K、43K、47K、51K、56K、62K、68K、75K、82K、91K、100K、110K、120K、130K、150K、160K、180K、200K、220K、240K、270K、300K、330K、360K、390K、430K、470K、510K、560K、620K、680K、750K、820K、910K、1M、1.1M、1.2M、1.3M、1.5M、1.6M、1.8M,,,,,,,,,,,,,\r\n采购策略,,,,,,,,,,,,,,,,,\r\n优选,厚声,,,,,,,,,,,,,,,,\r\n推荐,大毅,国巨,,,,,,,,,,,,,,,\r\n",
      "rows": [
        {
          "一": "序号",
          "采样电阻": "机型",
          "Column_3": "使用位置",
          "Column_4": "编码",
          "Column_5": "描述",
          "Column_6": "制造商名称",
          "Column_7": "制造商料号",
          "Column_8": "优选等级",
          "Column_9": "封装",
          "Column_10": "类型",
          "Column_11": "标称阻值",
          "Column_12": "精度(%)",
          "Column_13": "额定功率",
          "Column_14": "最大工作电压(V)",
          "Column_15": "备注",
          "Column_16": "",
          "Column_17": "",
          "Column_18": ""
        },
        {
          "一": "1",
          "采样电阻": "主机",
          "Column_3": "风机电流、充电IC输入/出电流",
          "Column_4": "04160100000105",
          "Column_5": "Resistor_Metal Foil_0.01R_1 %_1206_PE1206FKE470R01Z_Yageo",
          "Column_6": "国巨",
          "Column_7": "PE1206FKE470R01Z",
          "Column_8": "2-推荐",
          "Column_9": "1206",
          "Column_10": "Metal Foil",
          "Column_11": "0.01R",
          "Column_12": "0.01",
          "Column_13": "1W",
          "Column_14": "",
          "Column_15": "",
          "Column_16": "",
          "Column_17": "",
          "Column_18": ""
        },
        {
          "一": "1",
          "采样电阻": "主机",
          "Column_3": "风机电流、充电IC输入/出电流",
          "Column_4": "04160100000201",
          "Column_5": "Resistor_Metal Film_0.01R_1 %_1206_RLM12FTCMR010_TA-I",
          "Column_6": "大毅",
          "Column_7": "RLM12FTCMR010",
          "Column_8": "2-推荐",
          "Column_9": "1206",
          "Column_10": "Metal Film",
          "Column_11": "0.01R",
          "Column_12": "0.01",
          "Column_13": "1W",
          "Column_14": "",
          "Column_15": "",
          "Column_16": "",
          "Column_17": "",
          "Column_18": ""
        },
        {
          "一": "1",
          "采样电阻": "主机",
          "Column_3": "风机电流、充电IC输入/出电流",
          "Column_4": "04160100001143",
          "Column_5": "Resistor_Metal Foil_0.01R_1 %_1206_MS061WF100MT5E_Uni-Royal",
          "Column_6": "厚声",
          "Column_7": "MS061WF100MT5E",
          "Column_8": "1-优选",
          "Column_9": "1206",
          "Column_10": "Metal Foil",
          "Column_11": "0.01R",
          "Column_12": "0.01",
          "Column_13": "1W",
          "Column_14": "",
          "Column_15": "",
          "Column_16": "",
          "Column_17": "",
          "Column_18": ""
        },
        {
          "一": "2",
          "采样电阻": "主机",
          "Column_3": "整机充放电流检测",
          "Column_4": "04160100001019",
          "Column_5": "Resistor_Metal Plate / Grid_0.02R_1 %_1206_PA1206FRF470R02L_Yageo",
          "Column_6": "国巨",
          "Column_7": "PA1206FRF470R02L",
          "Column_8": "2-推荐",
          "Column_9": "1206",
          "Column_10": "Metal Plate / Grid",
          "Column_11": "0.02R",
          "Column_12": "0.01",
          "Column_13": "1W",
          "Column_14": "",
          "Column_15": "",
          "Column_16": "",
          "Column_17": "",
          "Column_18": ""
        },
        {
          "一": "2",
          "采样电阻": "主机",
          "Column_3": "整机充放电流检测",
          "Column_4": "04160100001180",
          "Column_5": "Resistor_Metal Foil_0.02R_1 %_1206_RLM12FTCMR020_TA-I",
          "Column_6": "大毅",
          "Column_7": "RLM12FTCMR020",
          "Column_8": "2-推荐",
          "Column_9": "1206",
          "Column_10": "Metal Foil",
          "Column_11": "0.02R",
          "Column_12": "0.01",
          "Column_13": "1W",
          "Column_14": "",
          "Column_15": "",
          "Column_16": "",
          "Column_17": "",
          "Column_18": ""
        },
        {
          "一": "2",
          "采样电阻": "主机",
          "Column_3": "整机充放电流检测",
          "Column_4": "04160100001178",
          "Column_5": "Resistor_Metal Foil_0.02R_1 %_1206_MS061WF200MT5E_Uni-Royal",
          "Column_6": "厚声",
          "Column_7": "MS061WF200MT5E",
          "Column_8": "1-优选",
          "Column_9": "1206",
          "Column_10": "Metal Foil",
          "Column_11": "0.02R",
          "Column_12": "0.01",
          "Column_13": "1W",
          "Column_14": "",
          "Column_15": "",
          "Column_16": "",
          "Column_17": "",
          "Column_18": ""
        },
        {
          "一": "3",
          "采样电阻": "主机",
          "Column_3": "驱动轮电流检测",
          "Column_4": "04160100000106",
          "Column_5": "Resistor_Thick Film_0.033R_1 %_1210_RL1210FR-070R033L_Yageo",
          "Column_6": "国巨",
          "Column_7": "RL1210FR-070R033L",
          "Column_8": "4-新品禁用",
          "Column_9": "1210",
          "Column_10": "Thick Film",
          "Column_11": "0.033R",
          "Column_12": "0.01",
          "Column_13": "1/2W",
          "Column_14": "200 V",
          "Column_15": "归一到2组0.02R",
          "Column_16": "",
          "Column_17": "",
          "Column_18": ""
        },
        {
          "一": "3",
          "采样电阻": "主机",
          "Column_3": "驱动轮电流检测",
          "Column_4": "04160100001132",
          "Column_5": "Resistor_Thick Film_0.033R_1 %_1210_1210W2F330MT5E_Uni-Royal",
          "Column_6": "厚声",
          "Column_7": "1210W2F330MT5E",
          "Column_8": "4-新品禁用",
          "Column_9": "1210",
          "Column_10": "Thick Film",
          "Column_11": "0.033R",
          "Column_12": "0.01",
          "Column_13": "1/2W",
          "Column_14": "200 V",
          "Column_15": "归一到2组0.02R",
          "Column_16": "",
          "Column_17": "",
          "Column_18": ""
        },
        {
          "一": "4",
          "采样电阻": "基站",
          "Column_3": "清水泵、蠕动泵、自动下水泵",
          "Column_4": "04160100001228",
          "Column_5": "Resistor_Thick Film_0.05R_1 %_1210_RL1210FR-070R05L_Yageo",
          "Column_6": "国巨",
          "Column_7": "RL1210FR-070R05L",
          "Column_8": "4-新品禁用",
          "Column_9": "1210",
          "Column_10": "Thick Film",
          "Column_11": "0.05R",
          "Column_12": "0.01",
          "Column_13": "1/2W",
          "Column_14": "",
          "Column_15": "归一到2组0.02R",
          "Column_16": "",
          "Column_17": "",
          "Column_18": ""
        },
        {
          "一": "4",
          "采样电阻": "基站",
          "Column_3": "清水泵、蠕动泵、自动下水泵",
          "Column_4": "04160100000799",
          "Column_5": "Resistor_Thick Film_0.05R_1 %_1210_1210W2F500MT5E_Uni-Royal",
          "Column_6": "厚声",
          "Column_7": "1210W2F500MT5E",
          "Column_8": "4-新品禁用",
          "Column_9": "1210",
          "Column_10": "Thick Film",
          "Column_11": "0.05R",
          "Column_12": "0.01",
          "Column_13": "1/2W",
          "Column_14": "200 V",
          "Column_15": "归一到2组0.02R",
          "Column_16": "",
          "Column_17": "",
          "Column_18": ""
        },
        {
          "一": "5",
          "采样电阻": "基站",
          "Column_3": "主机充电电流",
          "Column_4": "04160100001048",
          "Column_5": "Resistor_Metal Plate / Grid_0.05R_1 %_1206_PA1206FRF470R05L_Yageo",
          "Column_6": "国巨",
          "Column_7": "PA1206FRF470R05L",
          "Column_8": "4-新品禁用",
          "Column_9": "1206",
          "Column_10": "Metal Film",
          "Column_11": "0.05R",
          "Column_12": "0.01",
          "Column_13": "1W",
          "Column_14": "",
          "Column_15": "归一到2组0.02R",
          "Column_16": "",
          "Column_17": "",
          "Column_18": ""
        },
        {
          "一": "5",
          "采样电阻": "基站",
          "Column_3": "主机充电电流",
          "Column_4": "04160100001049",
          "Column_5": "Resistor_Metal Foil_0.05R_1 %_1206_RLM12FTCMR050_TA-I",
          "Column_6": "大毅",
          "Column_7": "RLM12FTCMR050",
          "Column_8": "4-新品禁用",
          "Column_9": "1206",
          "Column_10": "Metal Film",
          "Column_11": "0.05R",
          "Column_12": "0.01",
          "Column_13": "1W",
          "Column_14": "",
          "Column_15": "归一到2组0.02R",
          "Column_16": "",
          "Column_17": "",
          "Column_18": ""
        },
        {
          "一": "6",
          "采样电阻": "主机",
          "Column_3": "电池电流检测；风机电流检测",
          "Column_4": "04160100000008",
          "Column_5": "Resistor_Metal Foil_0.05R_1 %_2010_PE2010FKM7W0R05Z_Yageo",
          "Column_6": "国巨",
          "Column_7": "PE2010FKM7W0R05Z",
          "Column_8": "2-推荐",
          "Column_9": "2010",
          "Column_10": "Metal Foil",
          "Column_11": "0.05R",
          "Column_12": "0.01",
          "Column_13": "1W",
          "Column_14": "",
          "Column_15": "归一到2组0.02R",
          "Column_16": "",
          "Column_17": "",
          "Column_18": ""
        },
        {
          "一": "6",
          "采样电阻": "主机",
          "Column_3": "电池电流检测；风机电流检测",
          "Column_4": "04160100001229",
          "Column_5": "Resistor_Metal Foil_0.05R_1 %_2010_MS101WF500MT4E_Uni-Royal",
          "Column_6": "厚声",
          "Column_7": "MS101WF500MT4E",
          "Column_8": "5-淘汰",
          "Column_9": "2010",
          "Column_10": "Metal Foil",
          "Column_11": "0.05R",
          "Column_12": "0.01",
          "Column_13": "1W",
          "Column_14": "",
          "Column_15": "归一到2组0.02R",
          "Column_16": "",
          "Column_17": "",
          "Column_18": ""
        },
        {
          "一": "6",
          "采样电阻": "主机",
          "Column_3": "电池电流检测；风机电流检测",
          "Column_4": "04160100001231",
          "Column_5": "Resistor_Metal Foil_0.05R_1 %_2010_MS101AF500MT4E_Uni-Royal",
          "Column_6": "厚声",
          "Column_7": "MS101AF500MT4E",
          "Column_8": "3-普通",
          "Column_9": "2010",
          "Column_10": "Metal Foil",
          "Column_11": "0.05R",
          "Column_12": "0.01",
          "Column_13": "1.5W",
          "Column_14": "",
          "Column_15": "归一到2组0.02R",
          "Column_16": "",
          "Column_17": "",
          "Column_18": ""
        },
        {
          "一": "6",
          "采样电阻": "主机",
          "Column_3": "电池电流检测；风机电流检测",
          "Column_4": "04160100000213",
          "Column_5": "Resistor_Metal Foil_0.05R_1 %_2010_STE2010M1W5R050F_Walter",
          "Column_6": "华德",
          "Column_7": "STE2010M1W5R050F",
          "Column_8": "3-普通",
          "Column_9": "2010",
          "Column_10": "Metal Plate / Grid",
          "Column_11": "0.05R",
          "Column_12": "0.01",
          "Column_13": "1.5W",
          "Column_14": "",
          "Column_15": "归一到2组0.02R",
          "Column_16": "",
          "Column_17": "",
          "Column_18": ""
        },
        {
          "一": "7",
          "采样电阻": "基站",
          "Column_3": "电解水",
          "Column_4": "04160100000719",
          "Column_5": "Resistor_Thick_0.2R_1206W4F200LT5E_UNI-ROYAL",
          "Column_6": "厚声",
          "Column_7": "1206W4F200LT5E",
          "Column_8": "1-优选",
          "Column_9": "1206",
          "Column_10": "Thick Film",
          "Column_11": "0.2R",
          "Column_12": "0.01",
          "Column_13": "1/4W",
          "Column_14": "200 V",
          "Column_15": "电解水恒流500mA驱动，电解水用0.33R检流电阻在700~800TDS水质情况下会触发欠压保护，需要更换为0.2R检流电阻  ",
          "Column_16": "",
          "Column_17": "",
          "Column_18": ""
        },
        {
          "一": "7",
          "采样电阻": "基站",
          "Column_3": "电解水",
          "Column_4": "04160100001230",
          "Column_5": "Resistor_Thick Film_0.2R_1 %_1206_RL1206FR-070R2L_Yageo",
          "Column_6": "国巨",
          "Column_7": "RL1206FR-070R2L",
          "Column_8": "2-推荐",
          "Column_9": "1206",
          "Column_10": "Thick Film",
          "Column_11": "0.2R",
          "Column_12": "0.01",
          "Column_13": "1/4W",
          "Column_14": "200 V",
          "Column_15": "电解水恒流500mA驱动，电解水用0.33R检流电阻在700~800TDS水质情况下会触发欠压保护，需要更换为0.2R检流电阻  ",
          "Column_16": "",
          "Column_17": "",
          "Column_18": ""
        },
        {
          "一": "8",
          "采样电阻": "主机、基站",
          "Column_3": "自动上水电磁阀采样、边刷电流检测、进水泵/出水泵电流检测、电磁阀采样",
          "Column_4": "04160100001153",
          "Column_5": "Resistor_Metal Film_0.33R_1 %_1206_TL06W2F330LT5E_Uni-Royal",
          "Column_6": "厚声",
          "Column_7": "TL06W2F330LT5E",
          "Column_8": "1-优选",
          "Column_9": "1206",
          "Column_10": "Metal Film",
          "Column_11": "0.33R",
          "Column_12": "0.01",
          "Column_13": "1/2W",
          "Column_14": "",
          "Column_15": "",
          "Column_16": "",
          "Column_17": "",
          "Column_18": ""
        },
        {
          "一": "8",
          "采样电阻": "主机、基站",
          "Column_3": "自动上水电磁阀采样、边刷电流检测、进水泵/出水泵电流检测、电磁阀采样",
          "Column_4": "04160100000141",
          "Column_5": "Resistor_Thick Film_0.33R_1 %_1206_RL12FTNR330_TA-I",
          "Column_6": "大毅",
          "Column_7": "RL12FTNR330",
          "Column_8": "2-推荐",
          "Column_9": "1206",
          "Column_10": "alloy film chip",
          "Column_11": "0.33R",
          "Column_12": "0.01",
          "Column_13": "1/2W",
          "Column_14": "",
          "Column_15": "",
          "Column_16": "",
          "Column_17": "",
          "Column_18": ""
        },
        {
          "一": "8",
          "采样电阻": "主机、基站",
          "Column_3": "自动上水电磁阀采样、边刷电流检测、进水泵/出水泵电流检测、电磁阀采样",
          "Column_4": "04160100001244",
          "Column_5": "Resistor_Metal Film_0.33R_1 %_1206_PE1206FRF7W0R33L_Yageo",
          "Column_6": "国巨",
          "Column_7": "PE1206FRF7W0R33L",
          "Column_8": "2-推荐",
          "Column_9": "1206",
          "Column_10": "Metal Film",
          "Column_11": "0.33R",
          "Column_12": "0.01",
          "Column_13": "1/2W",
          "Column_14": "",
          "Column_15": "",
          "Column_16": "",
          "Column_17": "",
          "Column_18": ""
        },
        {
          "一": "8",
          "采样电阻": "主机、基站",
          "Column_3": "自动上水电磁阀采样、边刷电流检测、进水泵/出水泵电流检测、电磁阀采样",
          "Column_4": "04160100001292",
          "Column_5": "Resistor_Metal Foil_0.33R_1 %_1206_STE1206M1W0R330F_Walter",
          "Column_6": "华德",
          "Column_7": "STE1206M1W0R330F",
          "Column_8": "3-普通",
          "Column_9": "1206",
          "Column_10": "Metal Foil",
          "Column_11": "0.33R",
          "Column_12": "0.01",
          "Column_13": "1W",
          "Column_14": "",
          "Column_15": "边刷位置",
          "Column_16": "",
          "Column_17": "",
          "Column_18": ""
        },
        {
          "一": "8",
          "采样电阻": "主机、基站",
          "Column_3": "自动上水电磁阀采样、边刷电流检测、进水泵/出水泵电流检测、电磁阀采样",
          "Column_4": "04160100001293",
          "Column_5": "Resistor_Thick Film_0.33R_1 %_1206_RL1206FR-7W0R33L_Yageo",
          "Column_6": "国巨",
          "Column_7": "RL1206FR-7W0R33L",
          "Column_8": "3-普通",
          "Column_9": "1206",
          "Column_10": "Thick Film",
          "Column_11": "0.33R",
          "Column_12": "0.01",
          "Column_13": "1/2W",
          "Column_14": "",
          "Column_15": "非边刷位置可以使用厚膜电阻",
          "Column_16": "",
          "Column_17": "",
          "Column_18": ""
        },
        {
          "一": "9",
          "采样电阻": "基站",
          "Column_3": "基站两位三通阀、UV灯；主机补光灯AI-LED  AW9967DNR",
          "Column_4": "04160100000083",
          "Column_5": "Resistor_Thick Film_1R_1 %_1206_RC1206FR-071RL_Yageo",
          "Column_6": "国巨",
          "Column_7": "RC1206FR-071RL",
          "Column_8": "1-优选",
          "Column_9": "1206",
          "Column_10": "Thick Film",
          "Column_11": "1R",
          "Column_12": "0.01",
          "Column_13": "1/4W",
          "Column_14": "200 V",
          "Column_15": "",
          "Column_16": "",
          "Column_17": "",
          "Column_18": ""
        },
        {
          "一": "9",
          "采样电阻": "基站",
          "Column_3": "基站两位三通阀、UV灯；主机补光灯AI-LED  AW9967DNR",
          "Column_4": "04160100001164",
          "Column_5": "Resistor_Thick Film_1R_1 %_1206_1206W4F100KT5E_Uni-Royal",
          "Column_6": "厚声",
          "Column_7": "1206W4F100KT5E",
          "Column_8": "2-推荐",
          "Column_9": "1206",
          "Column_10": "Thick Film",
          "Column_11": "1R",
          "Column_12": "0.01",
          "Column_13": "1/4W",
          "Column_14": "200 V",
          "Column_15": "",
          "Column_16": "",
          "Column_17": "",
          "Column_18": ""
        },
        {
          "一": "10",
          "采样电阻": "基站",
          "Column_3": "UV灯驱动采样电阻",
          "Column_4": "04160100001236",
          "Column_5": "Resistor_Thick Film_1.6R_1 %_1206_HP06W2F160KT5E_Uni-Royal",
          "Column_6": "厚声",
          "Column_7": "HP06W2F160KT5E",
          "Column_8": "4-新品禁用",
          "Column_9": "1206",
          "Column_10": "Thick Film",
          "Column_11": "1.6R",
          "Column_12": "0.01",
          "Column_13": "1/2W",
          "Column_14": "200 V",
          "Column_15": "归一到11组的2R",
          "Column_16": "",
          "Column_17": "",
          "Column_18": ""
        },
        {
          "一": "10",
          "采样电阻": "基站",
          "Column_3": "UV灯驱动采样电阻",
          "Column_4": "04160100001237",
          "Column_5": "Resistor_Thick Film_1.6R_1 %_1206_RC1206FR-071R6L_Yageo",
          "Column_6": "国巨",
          "Column_7": "RC1206FR-071R6L",
          "Column_8": "4-新品禁用",
          "Column_9": "1206",
          "Column_10": "Thick Film",
          "Column_11": "1.6R",
          "Column_12": "0.01",
          "Column_13": "1/2W",
          "Column_14": "200 V",
          "Column_15": "归一到11组的2R",
          "Column_16": "",
          "Column_17": "",
          "Column_18": ""
        },
        {
          "一": "10",
          "采样电阻": "基站",
          "Column_3": "UV灯驱动采样电阻",
          "Column_4": "04160100001238",
          "Column_5": "Resistor_Thick Film_1.6R_1 %_1206_RMH12FT1R60_TA-I",
          "Column_6": "大毅",
          "Column_7": "RMH12FT1R60",
          "Column_8": "4-新品禁用",
          "Column_9": "1206",
          "Column_10": "Thick Film",
          "Column_11": "1.6R",
          "Column_12": "0.01",
          "Column_13": "1/2W",
          "Column_14": "200 V",
          "Column_15": "归一到11组的2R",
          "Column_16": "",
          "Column_17": "",
          "Column_18": ""
        },
        {
          "一": "11",
          "采样电阻": "主机",
          "Column_3": "补光灯限流电阻",
          "Column_4": "04160100000798",
          "Column_5": "Resistor_Thick Film_2R_1 %_1206_1206W4F200KT5E_Uni-Royal",
          "Column_6": "厚声",
          "Column_7": "1206W4F200KT5E",
          "Column_8": "1-优选",
          "Column_9": "1206",
          "Column_10": "Thick Film",
          "Column_11": "2R",
          "Column_12": "0.01",
          "Column_13": "1/4W",
          "Column_14": "200 V",
          "Column_15": "",
          "Column_16": "",
          "Column_17": "",
          "Column_18": ""
        },
        {
          "一": "11",
          "采样电阻": "主机",
          "Column_3": "补光灯限流电阻",
          "Column_4": "04160100001239",
          "Column_5": "Resistor_Thick Film_2R_1 %_1206_RC1206FR-072RL_Yageo",
          "Column_6": "国巨",
          "Column_7": "RC1206FR-072RL",
          "Column_8": "2-推荐",
          "Column_9": "1206",
          "Column_10": "Thick Film",
          "Column_11": "2R",
          "Column_12": "0.01",
          "Column_13": "1/4W",
          "Column_14": "200 V",
          "Column_15": "",
          "Column_16": "",
          "Column_17": "",
          "Column_18": ""
        },
        {
          "一": "二",
          "采样电阻": "普通电阻",
          "Column_3": "",
          "Column_4": "",
          "Column_5": "",
          "Column_6": "",
          "Column_7": "",
          "Column_8": "",
          "Column_9": "",
          "Column_10": "",
          "Column_11": "",
          "Column_12": "",
          "Column_13": "",
          "Column_14": "",
          "Column_15": "",
          "Column_16": "",
          "Column_17": "",
          "Column_18": ""
        },
        {
          "一": "",
          "采样电阻": "精度",
          "Column_3": "金属、厚膜电阻：优选1%；薄膜电阻：优选0.1%",
          "Column_4": "",
          "Column_5": "",
          "Column_6": "",
          "Column_7": "",
          "Column_8": "",
          "Column_9": "",
          "Column_10": "",
          "Column_11": "",
          "Column_12": "",
          "Column_13": "",
          "Column_14": "",
          "Column_15": "",
          "Column_16": "",
          "Column_17": "",
          "Column_18": ""
        },
        {
          "一": "",
          "采样电阻": "尺寸",
          "Column_3": "金属电阻尺寸：优选1206，其次：2010",
          "Column_4": "",
          "Column_5": "",
          "Column_6": "",
          "Column_7": "",
          "Column_8": "",
          "Column_9": "",
          "Column_10": "",
          "Column_11": "",
          "Column_12": "",
          "Column_13": "",
          "Column_14": "",
          "Column_15": "",
          "Column_16": "",
          "Column_17": "",
          "Column_18": ""
        },
        {
          "一": "",
          "采样电阻": "抗硫化电阻",
          "Column_3": "禁用",
          "Column_4": "",
          "Column_5": "",
          "Column_6": "",
          "Column_7": "",
          "Column_8": "",
          "Column_9": "",
          "Column_10": "",
          "Column_11": "",
          "Column_12": "",
          "Column_13": "",
          "Column_14": "",
          "Column_15": "",
          "Column_16": "",
          "Column_17": "",
          "Column_18": ""
        },
        {
          "一": "",
          "采样电阻": "阻值：",
          "Column_3": "E192 系列包含了 95 个基本阻值，分别为 1.0、1.1、1.2、1.3、1.5、1.6、1.8、2.0、2.2、2.4、2.7、3.0、3.3、3.6、3.9、4.3、4.7、5.1、5.6、6.2、6.8、7.5、8.2、9.1、10、11、12、13、15、16、18、20、22、24、27、30、33、36、39、43、47、51、56、62、68、75、82、91、100、110、120、130、150、160、180、200、220、240、270、300、330、360、390、430、470、510、560、620、680、750、820、910、1.0K、1.1K、1.2K、1.3K、1.5K、1.6K、1.8K、2.0K、2.2K、2.4K、2.7K、3.0K、3.3K、3.6K、3.9K、4.3K、4.7K、5.1K、5.6K、6.2K、6.8K、7.5K、8.2K、9.1K、10K、11K、12K、13K、15K、16K、18K、20K、22K、24K、27K、30K、33K、36K、39K、43K、47K、51K、56K、62K、68K、75K、82K、91K、100K、110K、120K、130K、150K、160K、180K、200K、220K、240K、270K、300K、330K、360K、390K、430K、470K、510K、560K、620K、680K、750K、820K、910K、1M、1.1M、1.2M、1.3M、1.5M、1.6M、1.8M",
          "Column_4": "E192 系列包含了 95 个基本阻值，分别为 1.0、1.1、1.2、1.3、1.5、1.6、1.8、2.0、2.2、2.4、2.7、3.0、3.3、3.6、3.9、4.3、4.7、5.1、5.6、6.2、6.8、7.5、8.2、9.1、10、11、12、13、15、16、18、20、22、24、27、30、33、36、39、43、47、51、56、62、68、75、82、91、100、110、120、130、150、160、180、200、220、240、270、300、330、360、390、430、470、510、560、620、680、750、820、910、1.0K、1.1K、1.2K、1.3K、1.5K、1.6K、1.8K、2.0K、2.2K、2.4K、2.7K、3.0K、3.3K、3.6K、3.9K、4.3K、4.7K、5.1K、5.6K、6.2K、6.8K、7.5K、8.2K、9.1K、10K、11K、12K、13K、15K、16K、18K、20K、22K、24K、27K、30K、33K、36K、39K、43K、47K、51K、56K、62K、68K、75K、82K、91K、100K、110K、120K、130K、150K、160K、180K、200K、220K、240K、270K、300K、330K、360K、390K、430K、470K、510K、560K、620K、680K、750K、820K、910K、1M、1.1M、1.2M、1.3M、1.5M、1.6M、1.8M",
          "Column_5": "E192 系列包含了 95 个基本阻值，分别为 1.0、1.1、1.2、1.3、1.5、1.6、1.8、2.0、2.2、2.4、2.7、3.0、3.3、3.6、3.9、4.3、4.7、5.1、5.6、6.2、6.8、7.5、8.2、9.1、10、11、12、13、15、16、18、20、22、24、27、30、33、36、39、43、47、51、56、62、68、75、82、91、100、110、120、130、150、160、180、200、220、240、270、300、330、360、390、430、470、510、560、620、680、750、820、910、1.0K、1.1K、1.2K、1.3K、1.5K、1.6K、1.8K、2.0K、2.2K、2.4K、2.7K、3.0K、3.3K、3.6K、3.9K、4.3K、4.7K、5.1K、5.6K、6.2K、6.8K、7.5K、8.2K、9.1K、10K、11K、12K、13K、15K、16K、18K、20K、22K、24K、27K、30K、33K、36K、39K、43K、47K、51K、56K、62K、68K、75K、82K、91K、100K、110K、120K、130K、150K、160K、180K、200K、220K、240K、270K、300K、330K、360K、390K、430K、470K、510K、560K、620K、680K、750K、820K、910K、1M、1.1M、1.2M、1.3M、1.5M、1.6M、1.8M",
          "Column_6": "",
          "Column_7": "",
          "Column_8": "",
          "Column_9": "",
          "Column_10": "",
          "Column_11": "",
          "Column_12": "",
          "Column_13": "",
          "Column_14": "",
          "Column_15": "",
          "Column_16": "",
          "Column_17": "",
          "Column_18": ""
        },
        {
          "一": "采购策略",
          "采样电阻": "",
          "Column_3": "",
          "Column_4": "",
          "Column_5": "",
          "Column_6": "",
          "Column_7": "",
          "Column_8": "",
          "Column_9": "",
          "Column_10": "",
          "Column_11": "",
          "Column_12": "",
          "Column_13": "",
          "Column_14": "",
          "Column_15": "",
          "Column_16": "",
          "Column_17": "",
          "Column_18": ""
        },
        {
          "一": "优选",
          "采样电阻": "厚声",
          "Column_3": "",
          "Column_4": "",
          "Column_5": "",
          "Column_6": "",
          "Column_7": "",
          "Column_8": "",
          "Column_9": "",
          "Column_10": "",
          "Column_11": "",
          "Column_12": "",
          "Column_13": "",
          "Column_14": "",
          "Column_15": "",
          "Column_16": "",
          "Column_17": "",
          "Column_18": ""
        },
        {
          "一": "推荐",
          "采样电阻": "大毅",
          "Column_3": "国巨",
          "Column_4": "",
          "Column_5": "",
          "Column_6": "",
          "Column_7": "",
          "Column_8": "",
          "Column_9": "",
          "Column_10": "",
          "Column_11": "",
          "Column_12": "",
          "Column_13": "",
          "Column_14": "",
          "Column_15": "",
          "Column_16": "",
          "Column_17": "",
          "Column_18": ""
        }
      ]
    }
  ]
}